Workbook

Sheet Read Me
A1: Marketing Performance Model
A3: Author | B3: RP Karthigayan - karthickoffical2009@gmail.com
A4: Purpose | B4: Answer one question: where should the next marketing dollar go?
A6: Assumptions | B6: Every lever in the model. Blue cells are inputs; yellow are the ones that move it most.
A7: Raw Data | B7: 72 rows: 6 channels x 12 months. The only sheet containing typed data.
A8: Channel Summary | B8: Per-channel CTR, CPC, CPL, CAC, ROAS, payback and share of spend vs share of customers.
A9: Monthly Trend | B9: Blended CAC and ROAS by month, with a seasonality read against the 12-month average.
A10: Reallocation Model | B10: Scenario: move 60% of the worst-CAC channel's budget to three cheaper channels at flat spend.
A12: How to use it | B12: Change Assumptions!B5 (average MRR) or B12 (share of budget moved) and every sheet recalculates.
A13: Data note | B13: This dataset is SIMULATED so the analysis can be published openly. The metric definitions and model structure are the ones used on real client data.
A14: Limits | B14: Last-touch attribution; first-year revenue rather than LTV; non-media 'spend' is production and commission cost so those CAC figures are not directly comparable with media CAC.

Sheet Assumptions
A1: Marketing Performance Model - Assumptions
A2: Edit only the blue cells. Yellow fill marks the assumptions that move the model most. Every other sheet references this one by cell, so nothing needs editing twice.
A4: Assumption | B4: Value | C4: Source / rationale
A5: Average MRR per customer | B5: 149 | C5: Client-provided average plan price.
A6: Gross margin | B6: 0.72 | C6: Used for payback only. Client finance estimate.
A7: Target CAC | B7: 250 | C7: Planning threshold agreed with marketing lead.
A8: Target ROAS (first-year revenue / spend) | B8: 5 | C8: Floor below which payback exceeds one quarter.
A9: Payback threshold (months) | B9: 6 | C9: Above this a channel is reviewed for cuts.
A11: REALLOCATION LEVERS
A12: Share of worst-CAC channel budget to move | B12: 0.6 | C12: Scenario lever. 100% would switch the channel off.
A13: Incremental CAC multiple - Partner / Agency | B13: 2.5 | C13: Diminishing returns on the next dollar.
A14: Incremental CAC multiple - Email / Lifecycle | B14: 3.6 | C14: Capacity-bound channel; next dollar is expensive.
A15: Incremental CAC multiple - SEO / Organic | B15: 3 | C15: Content cost rises as keyword difficulty rises.
A16: Growth ceiling - Partner / Agency | B16: 0.35 | C16: Max uplift on current customers within the year.
A17: Growth ceiling - Email / Lifecycle | B17: 0.15 | C17: Limited by list size, not budget.
A18: Growth ceiling - SEO / Organic | B18: 0.2 | C18: Two-quarter lag before compounding.
A19: Budget split to Partner / Agency | B19: 0.6 | C19: Of the released budget.
A20: Budget split to Email / Lifecycle | B20: 0.15 | C20: Of the released budget.
A21: Budget split to SEO / Organic | B21: 0.25 | C21: Of the released budget.
A22: First-year revenue retention factor | B22: 0.88 | C22: Churn adjustment: share of 12 months' MRR actually realised in year one.
A24: Data source: marketing_channel_performance.csv - a SIMULATED dataset built for portfolio publication. 72 rows, 6 channels x 12 months (Aug 2025 - Jul 2026).

Sheet Raw Data
A1: Month | B1: Channel | C1: Spend Usd | D1: Impressions | E1: Clicks | F1: Leads | G1: Qualified Leads | H1: New Customers | I1: New Mrr Usd | J1: First Year Revenue Usd
A2: 2025-08 | B2: Google Search Ads | C2: 18887.35 | D2: 102814 | E2: 4247 | F2: 402 | G2: 222 | H2: 43 | I2: 6838.74 | J2: 71986.3
A3: 2025-09 | B3: Google Search Ads | C3: 20782.71 | D3: 123682 | E3: 4980 | F3: 394 | G3: 210 | H3: 60 | I3: 8838.34 | J3: 94901.45
A4: 2025-10 | B4: Google Search Ads | C4: 19880.3 | D4: 136525 | E4: 5413 | F4: 441 | G4: 230 | H4: 53 | I4: 8091.52 | J4: 89965.92
A5: 2025-11 | B5: Google Search Ads | C5: 19136.11 | D5: 123172 | E5: 5372 | F5: 448 | G5: 235 | H5: 54 | I5: 8088.04 | J5: 91177.33
A6: 2025-12 | B6: Google Search Ads | C6: 20703.33 | D6: 142451 | E6: 4953 | F6: 330 | G6: 168 | H6: 40 | I6: 5835.35 | J6: 60272.56
A7: 2026-01 | B7: Google Search Ads | C7: 19450.23 | D7: 105282 | E7: 4566 | F7: 372 | G7: 187 | H7: 50 | I7: 7941.37 | J7: 89817.89
A8: 2026-02 | B8: Google Search Ads | C8: 19224.93 | D8: 127829 | E8: 4939 | F8: 410 | G8: 207 | H8: 53 | I8: 7959.38 | J8: 89103.79
A9: 2026-03 | B9: Google Search Ads | C9: 17671.14 | D9: 126140 | E9: 4174 | F9: 332 | G9: 179 | H9: 41 | I9: 6500.34 | J9: 70606.13
A10: 2026-04 | B10: Google Search Ads | C10: 17983.38 | D10: 102166 | E10: 3911 | F10: 349 | G10: 152 | H10: 44 | I10: 6403.32 | J10: 68848.93
A11: 2026-05 | B11: Google Search Ads | C11: 19004.72 | D11: 106245 | E11: 4503 | F11: 392 | G11: 202 | H11: 47 | I11: 6488.01 | J11: 67940.32
A12: 2026-06 | B12: Google Search Ads | C12: 22812.91 | D12: 144902 | E12: 5903 | F12: 445 | G12: 236 | H12: 61 | I12: 9198.78 | J12: 101067.54
A13: 2026-07 | B13: Google Search Ads | C13: 22241.61 | D13: 159973 | E13: 5590 | F13: 527 | G13: 236 | H13: 77 | I13: 11298.5 | J13: 119635.8
... A73: 2026-07 | B73: Partner / Agency | C73: 8348.33 | D73: 80362 | E73: 2605 | F73: 432 | G73: 217 | H73: 114 | I73: 16861.04 | J73: 170568.88

Sheet Channel Summary
A1: Channel scorecard - full 12 months
A2: Every figure is a formula over Raw Data. Change a number there and this sheet moves. CPC is blank for non-media channels: their 'spend' is production and commission cost, so a cost-per-click would not mean anything.
A4: Channel | B4: Spend | C4: Impressions | D4: Clicks | E4: Leads | F4: Qualified | G4: Customers | H4: First-yr revenue | I4: CTR | J4: CPC | K4: CPL | L4: CAC | M4: Lead>Cust | N4: ROAS | O4: Payback (mo) | P4: % of spend | Q4: % of cust. | R4: Action
A5: Email / Lifecycle | B5: =SUMIF('Raw Data'!$B$2:$B$73,$A5,'Raw Data'!$C$2:$C$73) -> 19697.43 | C5: =SUMIF('Raw Data'!$B$2:$B$73,$A5,'Raw Data'!$D$2:$D$73) -> 199761 | D5: =SUMIF('Raw Data'!$B$2:$B$73,$A5,'Raw Data'!$E$2:$E$73) -> 17373 | E5: =SUMIF('Raw Data'!$B$2:$B$73,$A5,'Raw Data'!$F$2:$F$73) -> 2043 | F5: =SUMIF('Raw Data'!$B$2:$B$73,$A5,'Raw Data'!$G$2:$G$73) -> 990 | G5: =SUMIF('Raw Data'!$B$2:$B$73,$A5,'Raw Data'!$H$2:$H$73) -> 411 | H5: =SUMIF('Raw Data'!$B$2:$B$73,$A5,'Raw Data'!$J$2:$J$73) -> 668790.76 | I5: =IFERROR(D5/C5,0) -> 0.086968928 | J5: =IF(ISNUMBER(MATCH($A5,{"Google Search Ads";"Meta Ads";"LinkedIn Ads"},0)),IFERROR(B5/D5,0),"") | K5: =IFERROR(B5/E5,0) -> 9.6414244 | L5: =IFERROR(B5/G5,0) -> 47.92562 | M5: =IFERROR(G5/E5,0) -> 0.20117474 | N5: =IFERROR(H5/B5,0) -> 33.953199 | O5: =IFERROR(L5/(Assumptions!$B$5*Assumptions!$B$6),0) -> 0.44673397 | P5: =IFERROR(B5/$B$11,0) -> 0.027770877 | Q5: =IFERROR(G5/$G$11,0) -> 0.13344156 | R5: =IF(O5>Assumptions!$B$9,"Cut",IF(L5>Assumptions!$B$7,"Hold","Fund")) -> Fund
A6: Partner / Agency | B6: =SUMIF('Raw Data'!$B$2:$B$73,$A6,'Raw Data'!$C$2:$C$73) -> 82253.26 | C6: =SUMIF('Raw Data'!$B$2:$B$73,$A6,'Raw Data'!$D$2:$D$73) -> 787885 | D6: =SUMIF('Raw Data'!$B$2:$B$73,$A6,'Raw Data'!$E$2:$E$73) -> 23916 | E6: =SUMIF('Raw Data'!$B$2:$B$73,$A6,'Raw Data'!$F$2:$F$73) -> 3464 | F6: =SUMIF('Raw Data'!$B$2:$B$73,$A6,'Raw Data'!$G$2:$G$73) -> 1709 | G6: =SUMIF('Raw Data'!$B$2:$B$73,$A6,'Raw Data'!$H$2:$H$73) -> 944 | H6: =SUMIF('Raw Data'!$B$2:$B$73,$A6,'Raw Data'!$J$2:$J$73) -> 1449595.7 | I6: =IFERROR(D6/C6,0) -> 0.030354684 | J6: =IF(ISNUMBER(MATCH($A6,{"Google Search Ads";"Meta Ads";"LinkedIn Ads"},0)),IFERROR(B6/D6,0),"") | K6: =IFERROR(B6/E6,0) -> 23.745167 | L6: =IFERROR(B6/G6,0) -> 87.132691 | M6: =IFERROR(G6/E6,0) -> 0.27251732 | N6: =IFERROR(H6/B6,0) -> 17.623565 | O6: =IFERROR(L6/(Assumptions!$B$5*Assumptions!$B$6),0) -> 0.81219883 | P6: =IFERROR(B6/$B$11,0) -> 0.11596666 | Q6: =IFERROR(G6/$G$11,0) -> 0.30649351 | R6: =IF(O6>Assumptions!$B$9,"Cut",IF(L6>Assumptions!$B$7,"Hold","Fund")) -> Fund
A7: SEO / Organic | B7: =SUMIF('Raw Data'!$B$2:$B$73,$A7,'Raw Data'!$C$2:$C$73) -> 57523.92 | C7: =SUMIF('Raw Data'!$B$2:$B$73,$A7,'Raw Data'!$D$2:$D$73) -> 529703 | D7: =SUMIF('Raw Data'!$B$2:$B$73,$A7,'Raw Data'!$E$2:$E$73) -> 31845 | E7: =SUMIF('Raw Data'!$B$2:$B$73,$A7,'Raw Data'!$F$2:$F$73) -> 2352 | F7: =SUMIF('Raw Data'!$B$2:$B$73,$A7,'Raw Data'!$G$2:$G$73) -> 1139 | G7: =SUMIF('Raw Data'!$B$2:$B$73,$A7,'Raw Data'!$H$2:$H$73) -> 432 | H7: =SUMIF('Raw Data'!$B$2:$B$73,$A7,'Raw Data'!$J$2:$J$73) -> 691954.67 | I7: =IFERROR(D7/C7,0) -> 0.060118595 | J7: =IF(ISNUMBER(MATCH($A7,{"Google Search Ads";"Meta Ads";"LinkedIn Ads"},0)),IFERROR(B7/D7,0),"") | K7: =IFERROR(B7/E7,0) -> 24.457449 | L7: =IFERROR(B7/G7,0) -> 133.15722 | M7: =IFERROR(G7/E7,0) -> 0.18367347 | N7: =IFERROR(H7/B7,0) -> 12.02899 | O7: =IFERROR(L7/(Assumptions!$B$5*Assumptions!$B$6),0) -> 1.241212 | P7: =IFERROR(B7/$B$11,0) -> 0.081101428 | Q7: =IFERROR(G7/$G$11,0) -> 0.14025974 | R7: =IF(O7>Assumptions!$B$9,"Cut",IF(L7>Assumptions!$B$7,"Hold","Fund")) -> Fund
A8: Meta Ads | B8: =SUMIF('Raw Data'!$B$2:$B$73,$A8,'Raw Data'!$C$2:$C$73) -> 190502.46 | C8: =SUMIF('Raw Data'!$B$2:$B$73,$A8,'Raw Data'!$D$2:$D$73) -> 10684539 | D8: =SUMIF('Raw Data'!$B$2:$B$73,$A8,'Raw Data'!$E$2:$E$73) -> 145925 | E8: =SUMIF('Raw Data'!$B$2:$B$73,$A8,'Raw Data'!$F$2:$F$73) -> 7532 | F8: =SUMIF('Raw Data'!$B$2:$B$73,$A8,'Raw Data'!$G$2:$G$73) -> 3703 | G8: =SUMIF('Raw Data'!$B$2:$B$73,$A8,'Raw Data'!$H$2:$H$73) -> 539 | H8: =SUMIF('Raw Data'!$B$2:$B$73,$A8,'Raw Data'!$J$2:$J$73) -> 870170.38 | I8: =IFERROR(D8/C8,0) -> 0.013657585 | J8: =IF(ISNUMBER(MATCH($A8,{"Google Search Ads";"Meta Ads";"LinkedIn Ads"},0)),IFERROR(B8/D8,0),"") -> 1.305482 | K8: =IFERROR(B8/E8,0) -> 25.292414 | L8: =IFERROR(B8/G8,0) -> 353.43685 | M8: =IFERROR(G8/E8,0) -> 0.071561338 | N8: =IFERROR(H8/B8,0) -> 4.5677645 | O8: =IFERROR(L8/(Assumptions!$B$5*Assumptions!$B$6),0) -> 3.2945269 | P8: =IFERROR(B8/$B$11,0) -> 0.2685843 | Q8: =IFERROR(G8/$G$11,0) -> 0.175 | R8: =IF(O8>Assumptions!$B$9,"Cut",IF(L8>Assumptions!$B$7,"Hold","Fund")) -> Hold
A9: Google Search Ads | B9: =SUMIF('Raw Data'!$B$2:$B$73,$A9,'Raw Data'!$C$2:$C$73) -> 237778.72 | C9: =SUMIF('Raw Data'!$B$2:$B$73,$A9,'Raw Data'!$D$2:$D$73) -> 1501181 | D9: =SUMIF('Raw Data'!$B$2:$B$73,$A9,'Raw Data'!$E$2:$E$73) -> 58551 | E9: =SUMIF('Raw Data'!$B$2:$B$73,$A9,'Raw Data'!$F$2:$F$73) -> 4842 | F9: =SUMIF('Raw Data'!$B$2:$B$73,$A9,'Raw Data'!$G$2:$G$73) -> 2464 | G9: =SUMIF('Raw Data'!$B$2:$B$73,$A9,'Raw Data'!$H$2:$H$73) -> 623 | H9: =SUMIF('Raw Data'!$B$2:$B$73,$A9,'Raw Data'!$J$2:$J$73) -> 1015324 | I9: =IFERROR(D9/C9,0) -> 0.039003291 | J9: =IF(ISNUMBER(MATCH($A9,{"Google Search Ads";"Meta Ads";"LinkedIn Ads"},0)),IFERROR(B9/D9,0),"") -> 4.0610531 | K9: =IFERROR(B9/E9,0) -> 49.107542 | L9: =IFERROR(B9/G9,0) -> 381.66729 | M9: =IFERROR(G9/E9,0) -> 0.12866584 | N9: =IFERROR(H9/B9,0) -> 4.2700371 | O9: =IFERROR(L9/(Assumptions!$B$5*Assumptions!$B$6),0) -> 3.5576742 | P9: =IFERROR(B9/$B$11,0) -> 0.33523782 | Q9: =IFERROR(G9/$G$11,0) -> 0.20227273 | R9: =IF(O9>Assumptions!$B$9,"Cut",IF(L9>Assumptions!$B$7,"Hold","Fund")) -> Hold
A10: LinkedIn Ads | B10: =SUMIF('Raw Data'!$B$2:$B$73,$A10,'Raw Data'!$C$2:$C$73) -> 121527.9 | C10: =SUMIF('Raw Data'!$B$2:$B$73,$A10,'Raw Data'!$D$2:$D$73) -> 2311200 | D10: =SUMIF('Raw Data'!$B$2:$B$73,$A10,'Raw Data'!$E$2:$E$73) -> 13968 | E10: =SUMIF('Raw Data'!$B$2:$B$73,$A10,'Raw Data'!$F$2:$F$73) -> 850 | F10: =SUMIF('Raw Data'!$B$2:$B$73,$A10,'Raw Data'!$G$2:$G$73) -> 411 | G10: =SUMIF('Raw Data'!$B$2:$B$73,$A10,'Raw Data'!$H$2:$H$73) -> 131 | H10: =SUMIF('Raw Data'!$B$2:$B$73,$A10,'Raw Data'!$J$2:$J$73) -> 207382.84 | I10: =IFERROR(D10/C10,0) -> 0.0060436137 | J10: =IF(ISNUMBER(MATCH($A10,{"Google Search Ads";"Meta Ads";"LinkedIn Ads"},0)),IFERROR(B10/D10,0),"") -> 8.700451 | K10: =IFERROR(B10/E10,0) -> 142.974 | L10: =IFERROR(B10/G10,0) -> 927.69389 | M10: =IFERROR(G10/E10,0) -> 0.15411765 | N10: =IFERROR(H10/B10,0) -> 1.7064628 | O10: =IFERROR(L10/(Assumptions!$B$5*Assumptions!$B$6),0) -> 8.6474077 | P10: =IFERROR(B10/$B$11,0) -> 0.17133892 | Q10: =IFERROR(G10/$G$11,0) -> 0.042532468 | R10: =IF(O10>Assumptions!$B$9,"Cut",IF(L10>Assumptions!$B$7,"Hold","Fund")) -> Cut
A11: All channels | B11: =SUM(B5:B10) -> 709283.69 | C11: =SUM(C5:C10) -> 16014269 | D11: =SUM(D5:D10) -> 291578 | E11: =SUM(E5:E10) -> 21083 | F11: =SUM(F5:F10) -> 10416 | G11: =SUM(G5:G10) -> 3080 | H11: =SUM(H5:H10) -> 4903218.3 | I11: =IFERROR(D11/C11,0) -> 0.018207387 | J11: ="" | K11: =IFERROR(B11/E11,0) -> 33.642446 | L11: =IFERROR(B11/G11,0) -> 230.28691 | M11: =IFERROR(G11/E11,0) -> 0.14608927 | N11: =IFERROR(H11/B11,0) -> 6.9129156 | O11: =IFERROR(L11/(Assumptions!$B$5*Assumptions!$B$6),0) -> 2.1465969 | P11: 1 | Q11: 1 | R11: -
A13: Payback uses Assumptions!B5 (average MRR) and B6 (gross margin). Fully loaded CAC would additionally carry marketing headcount, which this dataset does not contain.

Sheet Monthly Trend
A1: Blended monthly trend
A2: Seasonality read: compare each month's blended CAC against the 12-month average in column H.
A4: Month | B4: Spend | C4: Leads | D4: Customers | E4: First-yr revenue | F4: Blended CAC | G4: Blended ROAS | H4: CAC vs avg | I4: 3-mo rolling CAC | J4: Read
A5: 2025-08 | B5: =SUMIF('Raw Data'!$A$2:$A$73,$A5,'Raw Data'!$C$2:$C$73) -> 59331.49 | C5: =SUMIF('Raw Data'!$A$2:$A$73,$A5,'Raw Data'!$F$2:$F$73) -> 1837 | D5: =SUMIF('Raw Data'!$A$2:$A$73,$A5,'Raw Data'!$H$2:$H$73) -> 277 | E5: =SUMIF('Raw Data'!$A$2:$A$73,$A5,'Raw Data'!$J$2:$J$73) -> 434552.31 | F5: =IFERROR(B5/D5,0) -> 214.1931 | G5: =IFERROR(E5/B5,0) -> 7.3241429 | H5: =IFERROR(F5/AVERAGE($F$5:$F$16)-1,0) -> -0.078837047 | I5: =IFERROR(AVERAGE(F5:F5),0) -> 214.1931 | J5: =IF(H5>0.08,"Expensive - flex budget down",IF(H5<-0.05,"Efficient - lean in","In line")) -> Efficient - lean in
A6: 2025-09 | B6: =SUMIF('Raw Data'!$A$2:$A$73,$A6,'Raw Data'!$C$2:$C$73) -> 62519.42 | C6: =SUMIF('Raw Data'!$A$2:$A$73,$A6,'Raw Data'!$F$2:$F$73) -> 1831 | D6: =SUMIF('Raw Data'!$A$2:$A$73,$A6,'Raw Data'!$H$2:$H$73) -> 301 | E6: =SUMIF('Raw Data'!$A$2:$A$73,$A6,'Raw Data'!$J$2:$J$73) -> 455552.08 | F6: =IFERROR(B6/D6,0) -> 207.70571 | G6: =IFERROR(E6/B6,0) -> 7.2865692 | H6: =IFERROR(F6/AVERAGE($F$5:$F$16)-1,0) -> -0.10673684 | I6: =IFERROR(AVERAGE(F5:F6),0) -> 210.94941 | J6: =IF(H6>0.08,"Expensive - flex budget down",IF(H6<-0.05,"Efficient - lean in","In line")) -> Efficient - lean in
A7: 2025-10 | B7: =SUMIF('Raw Data'!$A$2:$A$73,$A7,'Raw Data'!$C$2:$C$73) -> 59070.71 | C7: =SUMIF('Raw Data'!$A$2:$A$73,$A7,'Raw Data'!$F$2:$F$73) -> 1772 | D7: =SUMIF('Raw Data'!$A$2:$A$73,$A7,'Raw Data'!$H$2:$H$73) -> 263 | E7: =SUMIF('Raw Data'!$A$2:$A$73,$A7,'Raw Data'!$J$2:$J$73) -> 425646.71 | F7: =IFERROR(B7/D7,0) -> 224.60346 | G7: =IFERROR(E7/B7,0) -> 7.2057152 | H7: =IFERROR(F7/AVERAGE($F$5:$F$16)-1,0) -> -0.034066074 | I7: =IFERROR(AVERAGE(F5:F7),0) -> 215.50076 | J7: =IF(H7>0.08,"Expensive - flex budget down",IF(H7<-0.05,"Efficient - lean in","In line")) -> In line
A8: 2025-11 | B8: =SUMIF('Raw Data'!$A$2:$A$73,$A8,'Raw Data'!$C$2:$C$73) -> 58831.63 | C8: =SUMIF('Raw Data'!$A$2:$A$73,$A8,'Raw Data'!$F$2:$F$73) -> 1743 | D8: =SUMIF('Raw Data'!$A$2:$A$73,$A8,'Raw Data'!$H$2:$H$73) -> 214 | E8: =SUMIF('Raw Data'!$A$2:$A$73,$A8,'Raw Data'!$J$2:$J$73) -> 347948.52 | F8: =IFERROR(B8/D8,0) -> 274.91416 | G8: =IFERROR(E8/B8,0) -> 5.9143104 | H8: =IFERROR(F8/AVERAGE($F$5:$F$16)-1,0) -> 0.18230108 | I8: =IFERROR(AVERAGE(F6:F8),0) -> 235.74111 | J8: =IF(H8>0.08,"Expensive - flex budget down",IF(H8<-0.05,"Efficient - lean in","In line")) -> Expensive - flex budget down
A9: 2025-12 | B9: =SUMIF('Raw Data'!$A$2:$A$73,$A9,'Raw Data'!$C$2:$C$73) -> 58608.33 | C9: =SUMIF('Raw Data'!$A$2:$A$73,$A9,'Raw Data'!$F$2:$F$73) -> 1581 | D9: =SUMIF('Raw Data'!$A$2:$A$73,$A9,'Raw Data'!$H$2:$H$73) -> 227 | E9: =SUMIF('Raw Data'!$A$2:$A$73,$A9,'Raw Data'!$J$2:$J$73) -> 375309.68 | F9: =IFERROR(B9/D9,0) -> 258.18648 | G9: =IFERROR(E9/B9,0) -> 6.4036918 | H9: =IFERROR(F9/AVERAGE($F$5:$F$16)-1,0) -> 0.11036168 | I9: =IFERROR(AVERAGE(F7:F9),0) -> 252.56803 | J9: =IF(H9>0.08,"Expensive - flex budget down",IF(H9<-0.05,"Efficient - lean in","In line")) -> Expensive - flex budget down
A10: 2026-01 | B10: =SUMIF('Raw Data'!$A$2:$A$73,$A10,'Raw Data'!$C$2:$C$73) -> 54666.1 | C10: =SUMIF('Raw Data'!$A$2:$A$73,$A10,'Raw Data'!$F$2:$F$73) -> 1697 | D10: =SUMIF('Raw Data'!$A$2:$A$73,$A10,'Raw Data'!$H$2:$H$73) -> 247 | E10: =SUMIF('Raw Data'!$A$2:$A$73,$A10,'Raw Data'!$J$2:$J$73) -> 397076.85 | F10: =IFERROR(B10/D10,0) -> 221.32024 | G10: =IFERROR(E10/B10,0) -> 7.2636762 | H10: =IFERROR(F10/AVERAGE($F$5:$F$16)-1,0) -> -0.048185941 | I10: =IFERROR(AVERAGE(F8:F10),0) -> 251.47363 | J10: =IF(H10>0.08,"Expensive - flex budget down",IF(H10<-0.05,"Efficient - lean in","In line")) -> In line
A11: 2026-02 | B11: =SUMIF('Raw Data'!$A$2:$A$73,$A11,'Raw Data'!$C$2:$C$73) -> 55169.78 | C11: =SUMIF('Raw Data'!$A$2:$A$73,$A11,'Raw Data'!$F$2:$F$73) -> 1551 | D11: =SUMIF('Raw Data'!$A$2:$A$73,$A11,'Raw Data'!$H$2:$H$73) -> 229 | E11: =SUMIF('Raw Data'!$A$2:$A$73,$A11,'Raw Data'!$J$2:$J$73) -> 366140.99 | F11: =IFERROR(B11/D11,0) -> 240.91607 | G11: =IFERROR(E11/B11,0) -> 6.6366223 | H11: =IFERROR(F11/AVERAGE($F$5:$F$16)-1,0) -> 0.036088247 | I11: =IFERROR(AVERAGE(F9:F11),0) -> 240.14093 | J11: =IF(H11>0.08,"Expensive - flex budget down",IF(H11<-0.05,"Efficient - lean in","In line")) -> In line
A12: 2026-03 | B12: =SUMIF('Raw Data'!$A$2:$A$73,$A12,'Raw Data'!$C$2:$C$73) -> 51789.49 | C12: =SUMIF('Raw Data'!$A$2:$A$73,$A12,'Raw Data'!$F$2:$F$73) -> 1491 | D12: =SUMIF('Raw Data'!$A$2:$A$73,$A12,'Raw Data'!$H$2:$H$73) -> 227 | E12: =SUMIF('Raw Data'!$A$2:$A$73,$A12,'Raw Data'!$J$2:$J$73) -> 353277.8 | F12: =IFERROR(B12/D12,0) -> 228.14753 | G12: =IFERROR(E12/B12,0) -> 6.8214188 | H12: =IFERROR(F12/AVERAGE($F$5:$F$16)-1,0) -> -0.018824367 | I12: =IFERROR(AVERAGE(F10:F12),0) -> 230.12795 | J12: =IF(H12>0.08,"Expensive - flex budget down",IF(H12<-0.05,"Efficient - lean in","In line")) -> In line
A13: 2026-04 | B13: =SUMIF('Raw Data'!$A$2:$A$73,$A13,'Raw Data'!$C$2:$C$73) -> 54838.53 | C13: =SUMIF('Raw Data'!$A$2:$A$73,$A13,'Raw Data'!$F$2:$F$73) -> 1589 | D13: =SUMIF('Raw Data'!$A$2:$A$73,$A13,'Raw Data'!$H$2:$H$73) -> 228 | E13: =SUMIF('Raw Data'!$A$2:$A$73,$A13,'Raw Data'!$J$2:$J$73) -> 353275.69 | F13: =IFERROR(B13/D13,0) -> 240.51987 | G13: =IFERROR(E13/B13,0) -> 6.4421072 | H13: =IFERROR(F13/AVERAGE($F$5:$F$16)-1,0) -> 0.034384335 | I13: =IFERROR(AVERAGE(F11:F13),0) -> 236.52782 | J13: =IF(H13>0.08,"Expensive - flex budget down",IF(H13<-0.05,"Efficient - lean in","In line")) -> In line
A14: 2026-05 | B14: =SUMIF('Raw Data'!$A$2:$A$73,$A14,'Raw Data'!$C$2:$C$73) -> 58499.69 | C14: =SUMIF('Raw Data'!$A$2:$A$73,$A14,'Raw Data'!$F$2:$F$73) -> 1661 | D14: =SUMIF('Raw Data'!$A$2:$A$73,$A14,'Raw Data'!$H$2:$H$73) -> 243 | E14: =SUMIF('Raw Data'!$A$2:$A$73,$A14,'Raw Data'!$J$2:$J$73) -> 375685.91 | F14: =IFERROR(B14/D14,0) -> 240.73947 | G14: =IFERROR(E14/B14,0) -> 6.4220154 | H14: =IFERROR(F14/AVERAGE($F$5:$F$16)-1,0) -> 0.035328736 | I14: =IFERROR(AVERAGE(F12:F14),0) -> 236.46896 | J14: =IF(H14>0.08,"Expensive - flex budget down",IF(H14<-0.05,"Efficient - lean in","In line")) -> In line
A15: 2026-06 | B15: =SUMIF('Raw Data'!$A$2:$A$73,$A15,'Raw Data'!$C$2:$C$73) -> 65951.51 | C15: =SUMIF('Raw Data'!$A$2:$A$73,$A15,'Raw Data'!$F$2:$F$73) -> 1903 | D15: =SUMIF('Raw Data'!$A$2:$A$73,$A15,'Raw Data'!$H$2:$H$73) -> 280 | E15: =SUMIF('Raw Data'!$A$2:$A$73,$A15,'Raw Data'!$J$2:$J$73) -> 472613.01 | F15: =IFERROR(B15/D15,0) -> 235.54111 | G15: =IFERROR(E15/B15,0) -> 7.1660681 | H15: =IFERROR(F15/AVERAGE($F$5:$F$16)-1,0) -> 0.012972579 | I15: =IFERROR(AVERAGE(F13:F15),0) -> 238.93348 | J15: =IF(H15>0.08,"Expensive - flex budget down",IF(H15<-0.05,"Efficient - lean in","In line")) -> In line
A16: 2026-07 | B16: =SUMIF('Raw Data'!$A$2:$A$73,$A16,'Raw Data'!$C$2:$C$73) -> 70007.01 | C16: =SUMIF('Raw Data'!$A$2:$A$73,$A16,'Raw Data'!$F$2:$F$73) -> 2427 | D16: =SUMIF('Raw Data'!$A$2:$A$73,$A16,'Raw Data'!$H$2:$H$73) -> 344 | E16: =SUMIF('Raw Data'!$A$2:$A$73,$A16,'Raw Data'!$J$2:$J$73) -> 546138.76 | F16: =IFERROR(B16/D16,0) -> 203.50875 | G16: =IFERROR(E16/B16,0) -> 7.8012011 | H16: =IFERROR(F16/AVERAGE($F$5:$F$16)-1,0) -> -0.12478639 | I16: =IFERROR(AVERAGE(F14:F16),0) -> 226.59644 | J16: =IF(H16>0.08,"Expensive - flex budget down",IF(H16<-0.05,"Efficient - lean in","In line")) -> Efficient - lean in
A17: Total / blended | B17: =SUM(B5:B16) -> 709283.69 | C17: =SUM(C5:C16) -> 21083 | D17: =SUM(D5:D16) -> 3080 | E17: =SUM(E5:E16) -> 4903218.3 | F17: =IFERROR(B17/D17,0) -> 230.28691 | G17: =IFERROR(E17/B17,0) -> 6.9129156

Sheet Reallocation Model
A1: Reallocation scenario - flat total spend
A2: Moves budget out of the worst-CAC channel into three cheaper ones. Incremental CAC is set worse than current CAC, and each receiver is capped by a growth ceiling, so the model cannot assume cheap customers scale forever. All levers live on Assumptions.
A4: Source channel | B4: Value
A5: Worst-CAC channel | B5: =INDEX('Channel Summary'!$A$5:$A$10,MATCH(MAX('Channel Summary'!$L$5:$L$10),'Channel Summary'!$L$5:$L$10,0)) -> LinkedIn Ads
A6: Its current spend | B6: =INDEX('Channel Summary'!$B$5:$B$10,MATCH($B$5,'Channel Summary'!$A$5:$A$10,0)) -> 121527.9
A7: Its current CAC | B7: =INDEX('Channel Summary'!$L$5:$L$10,MATCH($B$5,'Channel Summary'!$A$5:$A$10,0)) -> 927.69389
A8: Budget released | B8: =$B$6*Assumptions!$B$12 -> 72916.74
A9: Customers lost | B9: =IFERROR($B$8/$B$7,0) -> 78.6
A12: Receiving channel | B12: Budget added | C12: Current CAC | D12: Inc. CAC multiple | E12: Incremental CAC | F12: Uncapped customers | G12: Growth ceiling | H12: Modelled customers | I12: Ceiling applied?
A13: Partner / Agency | B13: =$B$8*Assumptions!$B$19 -> 43750.044 | C13: =INDEX('Channel Summary'!$L$5:$L$10,MATCH($A13,'Channel Summary'!$A$5:$A$10,0)) -> 87.132691 | D13: =Assumptions!$B$13 -> 2.5 | E13: =C13*D13 -> 217.83173 | F13: =IFERROR(B13/E13,0) -> 200.84331 | G13: =INDEX('Channel Summary'!$G$5:$G$10,MATCH($A13,'Channel Summary'!$A$5:$A$10,0))*Assumptions!$B$16 -> 330.4 | H13: =MIN(F13,G13) -> 200.84331 | I13: =IF(F13>G13,"Yes - capped","No") -> No
A14: Email / Lifecycle | B14: =$B$8*Assumptions!$B$20 -> 10937.511 | C14: =INDEX('Channel Summary'!$L$5:$L$10,MATCH($A14,'Channel Summary'!$A$5:$A$10,0)) -> 47.92562 | D14: =Assumptions!$B$14 -> 3.6 | E14: =C14*D14 -> 172.53223 | F14: =IFERROR(B14/E14,0) -> 63.394015 | G14: =INDEX('Channel Summary'!$G$5:$G$10,MATCH($A14,'Channel Summary'!$A$5:$A$10,0))*Assumptions!$B$17 -> 61.65 | H14: =MIN(F14,G14) -> 61.65 | I14: =IF(F14>G14,"Yes - capped","No") -> Yes - capped
A15: SEO / Organic | B15: =$B$8*Assumptions!$B$21 -> 18229.185 | C15: =INDEX('Channel Summary'!$L$5:$L$10,MATCH($A15,'Channel Summary'!$A$5:$A$10,0)) -> 133.15722 | D15: =Assumptions!$B$15 -> 3 | E15: =C15*D15 -> 399.47167 | F15: =IFERROR(B15/E15,0) -> 45.633236 | G15: =INDEX('Channel Summary'!$G$5:$G$10,MATCH($A15,'Channel Summary'!$A$5:$A$10,0))*Assumptions!$B$18 -> 86.4 | H15: =MIN(F15,G15) -> 45.633236 | I15: =IF(F15>G15,"Yes - capped","No") -> No
A16: Total gained | B16: =SUM(B13:B15) -> 72916.74 | H16: =SUM(H13:H15) -> 308.12654
A18: Customers gained | B18: =H16 -> 308.12654
A19: Customers lost from source channel | B19: =-$B$9 -> -78.6
A20: NET NEW CUSTOMERS | B20: =B18+B19 -> 229.52654
A21: Net new MRR | B21: =B20*Assumptions!$B$5 -> 34199.455
A22: Net new first-year revenue | B22: =B21*12*Assumptions!$B$22 -> 361146.24
A23: Blended CAC before | B23: ='Channel Summary'!$L$11 -> 230.28691
A24: Blended CAC after (flat spend) | B24: =IFERROR('Channel Summary'!$B$11/('Channel Summary'!$G$11+B20),0) -> 214.31576
A25: CAC improvement | B25: =IFERROR(B24/B23-1,0) -> -0.069353286
A27: Sanity check: total spend is unchanged, so any CAC improvement here comes from mix, not from a bigger budget.
A28: The source channel keeps 40% of its budget as a targeting test. In the funnel analysis its signups convert to paid at an above-average rate, so switching it off entirely would remove account quality this model does not price.
